cleanote/__init__.py
cleanote/dataset.py
cleanote/model.py
cleanote/pipeline.py
cleanote-0.4.0.dist-info/licenses/LICENSE
cleanote-0.4.0.dist-info/METADATA
cleanote-0.4.0.dist-info/WHEEL
cleanote-0.4.0.dist-info/top_level.txt
cleanote-0.4.0.dist-info/RECORD
