Metadata-Version: 2.4
Name: cleanote
Version: 0.4.0
Summary: CleanNote: preprocessing and harmonization of medical notes
Requires-Python: >=3.10
License-File: LICENSE
Requires-Dist: pydantic>=2
Requires-Dist: pyyaml
Requires-Dist: typer
Requires-Dist: rich
Requires-Dist: datasets
Requires-Dist: transformers>=4.41.0
Requires-Dist: torch>=2.3.0
Requires-Dist: accelerate>=0.30.0
Requires-Dist: safetensors>=0.4.3
Requires-Dist: spacy
Requires-Dist: matplotlib
Dynamic: license-file
